[
    {
        "id": 1,
        "ticker": "AAPL",
        "name": "Apple Inc.",
        "company_name": "Apple Inc.",
        "delisted": false,
        "industry": "Technology",
        "sector": "Consumer Electronics",
        "date_of_screening": "2025-01-27",
        "accounts_payables_annual": 123456789,
        "accounts_payables_quarter": 34567890,
        "accounts_payables_ttm": 98765432,
        "assets_non_current_ttm": 1250000000,
        "book_value_per_share": 145.67,
        "business_acquisitions_disposals_annual": 23456789,
        "capital_employed_annual": 500000000,
        "capital_expenditure_ttm": 200000000,
        "current_ratio_ttm": 1.5,
        "debt_ratio_ttm": 0.4
    },
    {
        "id": 2,
        "ticker": "GOOGL",
        "name": "Alphabet Inc.",
        "company_name": "Alphabet Inc.",
        "delisted": false,
        "industry": "Technology",
        "sector": "Internet Services",
        "date_of_screening": "2025-01-27",
        "accounts_payables_annual": 98765432,
        "accounts_payables_quarter": 12345678,
        "accounts_payables_ttm": 45678901,
        "assets_non_current_ttm": 1500000000,
        "book_value_per_share": 275.45,
        "business_acquisitions_disposals_annual": 56789012,
        "capital_employed_annual": 600000000,
        "capital_expenditure_ttm": 150000000,
        "current_ratio_ttm": 2.0,
        "debt_ratio_ttm": 0.3
    },
    {
        "id": 3,
        "ticker": "MSFT",
        "name": "Microsoft Corporation",
        "company_name": "Microsoft Corporation",
        "delisted": false,
        "industry": "Technology",
        "sector": "Software",
        "date_of_screening": "2025-01-27",
        "accounts_payables_annual": 87654321,
        "accounts_payables_quarter": 23456789,
        "accounts_payables_ttm": 56789012,
        "assets_non_current_ttm": 1300000000,
        "book_value_per_share": 310.23,
        "business_acquisitions_disposals_annual": 45678901,
        "capital_employed_annual": 700000000,
        "capital_expenditure_ttm": 300000000,
        "current_ratio_ttm": 1.8,
        "debt_ratio_ttm": 0.5
    },
    {
        "id": 4,
        "ticker": "TSLA",
        "name": "Tesla Inc.",
        "company_name": "Tesla Inc.",
        "delisted": false,
        "industry": "Automotive",
        "sector": "Electric Vehicles",
        "date_of_screening": "2025-01-27",
        "accounts_payables_annual": 54321098,
        "accounts_payables_quarter": 19876543,
        "accounts_payables_ttm": 67891234,
        "assets_non_current_ttm": 1800000000,
        "book_value_per_share": 205.34,
        "business_acquisitions_disposals_annual": 34567890,
        "capital_employed_annual": 450000000,
        "capital_expenditure_ttm": 400000000,
        "current_ratio_ttm": 2.5,
        "debt_ratio_ttm": 0.6
    },
    {
        "id": 5,
        "ticker": "AMZN",
        "name": "Amazon.com Inc.",
        "company_name": "Amazon.com Inc.",
        "delisted": false,
        "industry": "Retail",
        "sector": "E-Commerce",
        "date_of_screening": "2025-01-27",
        "accounts_payables_annual": 32165487,
        "accounts_payables_quarter": 14253678,
        "accounts_payables_ttm": 65478901,
        "assets_non_current_ttm": 2000000000,
        "book_value_per_share": 150.78,
        "business_acquisitions_disposals_annual": 76543210,
        "capital_employed_annual": 550000000,
        "capital_expenditure_ttm": 350000000,
        "current_ratio_ttm": 1.2,
        "debt_ratio_ttm": 0.7
    },
    {
        "id": 6,
        "ticker": "NVDA",
        "name": "NVIDIA Corporation",
        "company_name": "NVIDIA Corporation",
        "delisted": false,
        "industry": "Technology",
        "sector": "Semiconductors",
        "date_of_screening": "2025-01-27",
        "accounts_payables_annual": 19876543,
        "accounts_payables_quarter": 9876543,
        "accounts_payables_ttm": 21098765,
        "assets_non_current_ttm": 950000000,
        "book_value_per_share": 430.89,
        "business_acquisitions_disposals_annual": 23456789,
        "capital_employed_annual": 300000000,
        "capital_expenditure_ttm": 120000000,
        "current_ratio_ttm": 3.0,
        "debt_ratio_ttm": 0.25
    },
    {
        "id": 7,
        "ticker": "XOM",
        "name": "Exxon Mobil Corporation",
        "company_name": "Exxon Mobil Corporation",
        "delisted": false,
        "industry": "Energy",
        "sector": "Oil & Gas",
        "date_of_screening": "2025-01-27",
        "accounts_payables_annual": 65432109,
        "accounts_payables_quarter": 23456789,
        "accounts_payables_ttm": 45678912,
        "assets_non_current_ttm": 1200000000,
        "book_value_per_share": 95.67,
        "business_acquisitions_disposals_annual": 34567891,
        "capital_employed_annual": 700000000,
        "capital_expenditure_ttm": 500000000,
        "current_ratio_ttm": 1.7,
        "debt_ratio_ttm": 0.45
    },
    {
        "id": 8,
        "ticker": "PFE",
        "name": "Pfizer Inc.",
        "company_name": "Pfizer Inc.",
        "delisted": false,
        "industry": "Pharmaceuticals",
        "sector": "Healthcare",
        "date_of_screening": "2025-01-27",
        "accounts_payables_annual": 34567890,
        "accounts_payables_quarter": 12345678,
        "accounts_payables_ttm": 23456789,
        "assets_non_current_ttm": 890000000,
        "book_value_per_share": 65.34,
        "business_acquisitions_disposals_annual": 12567890,
        "capital_employed_annual": 400000000,
        "capital_expenditure_ttm": 300000000,
        "current_ratio_ttm": 1.4,
        "debt_ratio_ttm": 0.35
    },
    {
        "id": 9,
        "ticker": "JPM",
        "name": "JPMorgan Chase & Co.",
        "company_name": "JPMorgan Chase & Co.",
        "delisted": false,
        "industry": "Finance",
        "sector": "Banking",
        "date_of_screening": "2025-01-27",
        "accounts_payables_annual": 56789012,
        "accounts_payables_quarter": 12345678,
        "accounts_payables_ttm": 34567890,
        "assets_non_current_ttm": 2000000000,
        "book_value_per_share": 110.56,
        "business_acquisitions_disposals_annual": 67890123,
        "capital_employed_annual": 800000000,
        "capital_expenditure_ttm": 400000000,
        "current_ratio_ttm": 1.3,
        "debt_ratio_ttm": 0.5
    },
    {
        "id": 10,
        "ticker": "DIS",
        "name": "The Walt Disney Company",
        "company_name": "The Walt Disney Company",
        "delisted": false,
        "industry": "Entertainment",
        "sector": "Media",
        "date_of_screening": "2025-01-27",
        "accounts_payables_annual": 43210987,
        "accounts_payables_quarter": 12345678,
        "accounts_payables_ttm": 23456789,
        "assets_non_current_ttm": 850000000,
        "book_value_per_share": 120.34,
        "business_acquisitions_disposals_annual": 56789012,
        "capital_employed_annual": 550000000,
        "capital_expenditure_ttm": 250000000,
        "current_ratio_ttm": 1.9,
        "debt_ratio_ttm": 0.4
    }
]
